{"_path":"/databases/2-oracle-db","_dir":"databases","_draft":false,"_partial":false,"_locale":"","title":"Oracle DB","description":"Downloading Oracle DB:","date":"2024-02-16","author":"Aryan","body":{"type":"root","children":[{"type":"element","tag":"p","props":{},"children":[{"type":"text","value":"Downloading Oracle DB:"}]},{"type":"element","tag":"ol","props":{},"children":[{"type":"element","tag":"li","props":{},"children":[{"type":"text","value":"Create an account."}]},{"type":"element","tag":"li","props":{},"children":[{"type":"text","value":"Accept terms and condition on Docker registry: "},{"type":"element","tag":"a","props":{"href":"https://container-registry.oracle.com","rel":["nofollow"]},"children":[{"type":"text","value":"https://container-registry.oracle.com"}]}]}]},{"type":"element","tag":"p","props":{},"children":[{"type":"text","value":"click on database > enterprise > accept t&c"}]},{"type":"element","tag":"p","props":{},"children":[{"type":"element","tag":"img","props":{"alt":"accept terms and conditions","src":"/oracle-db/terms_and_condition.gif"},"children":[]}]},{"type":"element","tag":"ol","props":{"start":3},"children":[{"type":"element","tag":"li","props":{},"children":[{"type":"text","value":"login to registry "},{"type":"element","tag":"code","props":{"className":[]},"children":[{"type":"text","value":"docker login container-registry.oracle.com"}]}]},{"type":"element","tag":"li","props":{},"children":[{"type":"text","value":"Pull the image "},{"type":"element","tag":"code","props":{"className":[]},"children":[{"type":"text","value":"docker pull container-registry.oracle.com/database/enterprise:19.19.0.0"}]},{"type":"text","value":" for macos m1"}]},{"type":"element","tag":"li","props":{},"children":[{"type":"text","value":"Connect to my docker container "},{"type":"element","tag":"code","props":{"className":[]},"children":[{"type":"text","value":"docker exec -it my_oracle_db bash -c \"source /home/oracle/.bashrc; sqlplus /nolog\""}]}]},{"type":"element","tag":"li","props":{},"children":[{"type":"text","value":"Connect to DB"}]}]},{"type":"element","tag":"pre","props":{"code":"SQL> connect sys as sysdba;\nEnter password:\nConnected.\n"},"children":[{"type":"element","tag":"code","props":{"__ignoreMap":""},"children":[{"type":"text","value":"SQL> connect sys as sysdba;\nEnter password:\nConnected.\n"}]}]},{"type":"element","tag":"ol","props":{"start":7},"children":[{"type":"element","tag":"li","props":{},"children":[{"type":"text","value":"Alter the session"}]}]},{"type":"element","tag":"pre","props":{"code":"SQL> alter session set \"_ORACLE_SCRIPT\"=true;\n\nSession altered.\n"},"children":[{"type":"element","tag":"code","props":{"__ignoreMap":""},"children":[{"type":"text","value":"SQL> alter session set \"_ORACLE_SCRIPT\"=true;\n\nSession altered.\n"}]}]},{"type":"element","tag":"ol","props":{"start":8},"children":[{"type":"element","tag":"li","props":{},"children":[{"type":"text","value":"Create a new user aryan"}]}]},{"type":"element","tag":"pre","props":{"code":"SQL> create user aryan identified by aryan;\n\nUser created.\n"},"children":[{"type":"element","tag":"code","props":{"__ignoreMap":""},"children":[{"type":"text","value":"SQL> create user aryan identified by aryan;\n\nUser created.\n"}]}]},{"type":"element","tag":"ol","props":{"start":9},"children":[{"type":"element","tag":"li","props":{},"children":[{"type":"text","value":"Grant all preveleges to that user"}]}]},{"type":"element","tag":"pre","props":{"code":"SQL> GRANT ALL PRIVILEGES TO aryan;\n\nGrant succeeded.\n"},"children":[{"type":"element","tag":"code","props":{"__ignoreMap":""},"children":[{"type":"text","value":"SQL> GRANT ALL PRIVILEGES TO aryan;\n\nGrant succeeded.\n"}]}]},{"type":"element","tag":"ol","props":{"start":9},"children":[{"type":"element","tag":"li","props":{},"children":[{"type":"text","value":"Exec docker container"}]}]},{"type":"element","tag":"pre","props":{"code":"docker exec -it my_oracle_db bash\n"},"children":[{"type":"element","tag":"code","props":{"__ignoreMap":""},"children":[{"type":"text","value":"docker exec -it my_oracle_db bash\n"}]}]},{"type":"element","tag":"ol","props":{"start":10},"children":[{"type":"element","tag":"li","props":{},"children":[{"type":"text","value":"Connect to your new user"}]}]},{"type":"element","tag":"pre","props":{"code":"sqlplus aryan/aryan@localhost:1521/ORCLPDB1\n"},"children":[{"type":"element","tag":"code","props":{"__ignoreMap":""},"children":[{"type":"text","value":"sqlplus aryan/aryan@localhost:1521/ORCLPDB1\n"}]}]},{"type":"element","tag":"ol","props":{"start":11},"children":[{"type":"element","tag":"li","props":{},"children":[{"type":"text","value":"Now that you are connect with user aryan with password aryan. You can create a table"}]}]},{"type":"element","tag":"pre","props":{"code":"SQL> CREATE TABLE publisher\n  2  (\n  3  \"id_publisher\" NUMBER(3, 0) NOT NULL ENABLE,\n  4  \"name\" VARCHAR2(200 byte) NOT NULL ENABLE,\n  5  CONSTRAINT \"PUBLISHER_PK\" PRIMARY KEY (\"id_publisher\")\n  6  );\n\nTable created.\n","language":"sql","meta":"","className":["language-sql"]},"children":[{"type":"element","tag":"code","props":{"__ignoreMap":""},"children":[{"type":"text","value":"SQL> CREATE TABLE publisher\n  2  (\n  3  \"id_publisher\" NUMBER(3, 0) NOT NULL ENABLE,\n  4  \"name\" VARCHAR2(200 byte) NOT NULL ENABLE,\n  5  CONSTRAINT \"PUBLISHER_PK\" PRIMARY KEY (\"id_publisher\")\n  6  );\n\nTable created.\n"}]}]},{"type":"element","tag":"ol","props":{"start":12},"children":[{"type":"element","tag":"li","props":{},"children":[{"type":"text","value":"See what tables are accessible to aryan user"}]}]},{"type":"element","tag":"pre","props":{"code":"SQL> SELECT table_name FROM user_tables;\n\nTABLE_NAME\n------------------------------------------------------------\nPUBLISHER\n","language":"sql","meta":"","className":["language-sql"]},"children":[{"type":"element","tag":"code","props":{"__ignoreMap":""},"children":[{"type":"text","value":"SQL> SELECT table_name FROM user_tables;\n\nTABLE_NAME\n------------------------------------------------------------\nPUBLISHER\n"}]}]},{"type":"element","tag":"ol","props":{"start":13},"children":[{"type":"element","tag":"li","props":{},"children":[{"type":"text","value":"Showing the table"}]}]},{"type":"element","tag":"pre","props":{"code":"SQL> DESC publisher\n Name                      Null?    Type\n ----------------------------------------- -------- ----------------------------\n id_publisher                  NOT NULL NUMBER(3)\n name                      NOT NULL VARCHAR2(200)\n","language":"sql","meta":"","className":["language-sql"]},"children":[{"type":"element","tag":"code","props":{"__ignoreMap":""},"children":[{"type":"text","value":"SQL> DESC publisher\n Name                      Null?    Type\n ----------------------------------------- -------- ----------------------------\n id_publisher                  NOT NULL NUMBER(3)\n name                      NOT NULL VARCHAR2(200)\n"}]}]},{"type":"element","tag":"ol","props":{"start":14},"children":[{"type":"element","tag":"li","props":{},"children":[{"type":"text","value":"Inserting to the table"}]}]},{"type":"element","tag":"pre","props":{"code":"SQL> INSERT INTO publisher (\"id_publisher\", \"name\") VALUES (2, 'Another Publisher');\n\n1 row created.\n","language":"sql","meta":"","className":["language-sql"]},"children":[{"type":"element","tag":"code","props":{"__ignoreMap":""},"children":[{"type":"text","value":"SQL> INSERT INTO publisher (\"id_publisher\", \"name\") VALUES (2, 'Another Publisher');\n\n1 row created.\n"}]}]},{"type":"element","tag":"ol","props":{"start":15},"children":[{"type":"element","tag":"li","props":{},"children":[{"type":"text","value":"Updated the record on second ID"}]}]},{"type":"element","tag":"pre","props":{"code":"SQL> UPDATE publisher SET \"name\" = 'novo nome da editora' WHERE \"id_publisher\" = 2;\n\n1 row updated.\n","language":"sql","meta":"","className":["language-sql"]},"children":[{"type":"element","tag":"code","props":{"__ignoreMap":""},"children":[{"type":"text","value":"SQL> UPDATE publisher SET \"name\" = 'novo nome da editora' WHERE \"id_publisher\" = 2;\n\n1 row updated.\n"}]}]}],"toc":{"title":"","searchDepth":2,"depth":2,"links":[]}},"_type":"markdown","_id":"content:databases:2-oracle-db.md","_source":"content","_file":"databases/2-oracle-db.md","_extension":"md"}